piClusterNetworking/__init__.py
piClusterNetworking/client.py
piClusterNetworking/messages.py
piClusterNetworking/server.py
piClusterNetworking-0.0.4.dist-info/LICENSE
piClusterNetworking-0.0.4.dist-info/METADATA
piClusterNetworking-0.0.4.dist-info/WHEEL
piClusterNetworking-0.0.4.dist-info/top_level.txt
piClusterNetworking-0.0.4.dist-info/RECORD
